bittrex_websocket/__init__.py
bittrex_websocket/_abc.py
bittrex_websocket/_auxiliary.py
bittrex_websocket/_constants.py
bittrex_websocket/_exceptions.py
bittrex_websocket/_logger.py
bittrex_websocket/_queue_events.py
bittrex_websocket/constants.py
bittrex_websocket/websocket_client-aio.py
bittrex_websocket/websocket_client-testing.py
bittrex_websocket/websocket_client.py
bittrex_websocket_aio-0.0.0.3.0.dist-info/METADATA
bittrex_websocket_aio-0.0.0.3.0.dist-info/RECORD
bittrex_websocket_aio-0.0.0.3.0.dist-info/WHEEL
bittrex_websocket_aio-0.0.0.3.0.dist-info/top_level.txt
